scrapy_fake_useragent/__init__.py
scrapy_fake_useragent/middleware.py
scrapy_fake_useragent/user_agent_picker.py
scrapy_fake_useragent_fix-0.1.1.dist-info/LICENSE
scrapy_fake_useragent_fix-0.1.1.dist-info/METADATA
scrapy_fake_useragent_fix-0.1.1.dist-info/WHEEL
scrapy_fake_useragent_fix-0.1.1.dist-info/top_level.txt
scrapy_fake_useragent_fix-0.1.1.dist-info/RECORD
