Metadata-Version: 2.1
Name: scrapy-fake-useragent-fix
Version: 0.1.1
Summary: Use a random User-Agent provided by fake-useragent for every request
Home-page: https://github.com/Qiulin-Wang/scrapy-fake-useragent
Author: Neal Wong
Author-email: ibprnd@gmail.com
License: New BSD License
Keywords: scrapy proxy user-agent web-scraping
Platform: UNKNOWN
Classifier: Development Status :: 5 - Production/Stable
Classifier: Framework :: Scrapy
Classifier: Intended Audience :: Developers
Classifier: License :: OSI Approved :: BSD License
Classifier: Programming Language :: Python
Classifier: Topic :: Internet :: WWW/HTTP
Requires-Dist: fake-useragent
Requires-Dist: user-agents
